{
  "categorias": [
    {
      "id": 1,
      "titulo": "Bolos para festa",
      "cor": "#208aa4",
      "descricao": "Quem não ama um bolo de chocolate, bem molhadinho? #chocolovers",
      "link_extra": {
        "text": "Receitas de bolos para sua festa.",
        "url": "https://www.youtube.com/watch?v=1wSquygtVzE&t=1s"
      }
    },
    {
      "id": 2,
      "titulo": "Bolos simples",
      "cor": "#75b0c6",
      "descricao": "Quem não ama um bolo de chocolate, bem molhadinho? #chocolovers",
      "link_extra": {
        "text": "Bolo para o café.",
        "url": "https://www.youtube.com/watch?v=1wSquygtVzE&t=1s"
      }
    },
    {
      "id": 3,
      "titulo": "Tortas",
      "cor": "#f1c2b0",
      "descricao": "Quem não ama um bolo de chocolate, bem molhadinho? #chocolovers",
      "link_extra": {
        "text": "Tipos variados de tortas.",
        "url": "https://www.youtube.com/watch?v=1wSquygtVzE&t=1s"
      }
    },
    {
      "id": 4,
      "titulo": "Doces franceses",
      "cor": "#f6a588",
      "descricao": "Quem não ama um bolo de chocolate, bem molhadinho? #chocolovers",
      "link_extra": {
        "text": "Melhores receitas francesas.",
        "url": "https://www.youtube.com/watch?v=1wSquygtVzE&t=1s"
      }
    }
  ],
  "videos": [
    {
      "titulo": "Bolo de brigadeiro",
      "url": "https://www.youtube.com/watch?v=1wSquygtVzE&t=1s",
      "categoriaId": 1,
      "id": 3
    },
    {
      "titulo": "Bolo",
      "url": "https://www.youtube.com/watch?v=1wSquygtVzE&t=1s",
      "categoriaId": 1,
      "id": 5
    },
    {
      "titulo": "Bolo de cenoura",
      "url": "https://www.youtube.com/watch?v=-pRC-FQXLEI&t=1s",
      "categoriaId": 2,
      "id": 6
    },
    {
      "titulo": "Bolo Brownie",
      "url": "https://www.youtube.com/watch?v=BIyXExFZrFY",
      "categoriaId": 1,
      "id": 7
    },
    {
      "titulo": "Bolo Bem-casado",
      "url": "https://www.youtube.com/watch?v=2WR4B-GGYi0",
      "categoriaId": 1,
      "id": 8
    },
    {
      "titulo": "Naked cake",
      "url": "https://www.youtube.com/watch?v=t6v9a4IxkvQ",
      "categoriaId": 1,
      "id": 9
    },
    {
      "titulo": "Bolo pão de mel",
      "url": "https://www.youtube.com/watch?v=zH74H1bphBE",
      "categoriaId": 1,
      "id": 10
    },
    {
      "titulo": "Bolo branco",
      "url": "https://www.youtube.com/watch?v=lZHYHK86WNQ",
      "categoriaId": 1,
      "id": 11
    },
    {
      "titulo": "Bolo de fubá",
      "url": "https://www.youtube.com/watch?v=kchn5Dy9NTE",
      "categoriaId": 2,
      "id": 12
    },
    {
      "titulo": "Bolo de coco",
      "url": "https://www.youtube.com/watch?v=Sv1X419IFE8",
      "categoriaId": 2,
      "id": 13
    },
    {
      "titulo": "Bolo de banana",
      "url": "https://www.youtube.com/watch?v=PYt8O1lehxY",
      "categoriaId": 2,
      "id": 14
    },
    {
      "titulo": "Bolo de milho",
      "url": "https://www.youtube.com/watch?v=zuSQoTuCRck",
      "categoriaId": 2,
      "id": 15
    },
    {
      "titulo": "Macarons",
      "url": "https://www.youtube.com/watch?v=1pQ67sE6OP8",
      "categoriaId": 4,
      "id": 16
    },
    {
      "titulo": "Madeleines",
      "url": "https://www.youtube.com/watch?v=_eS2qElJxos&list=PLod7sGXa2u-gVK2sHdRjiq27CnvwdVYae&index=19",
      "categoriaId": 4,
      "id": 17
    },
    {
      "titulo": "Torta Oreo",
      "url": "https://www.youtube.com/watch?v=8VY1rN31c4I",
      "categoriaId": 3,
      "id": 18
    },
    {
      "titulo": "Torta holandesa",
      "url": "https://www.youtube.com/watch?v=mMQ2xwZzvCg",
      "categoriaId": 3,
      "id": 19
    },
    {
      "titulo": "Torta de limão",
      "url": "https://www.youtube.com/watch?v=f9xX9Vqre8I",
      "categoriaId": 3,
      "id": 20
    }
  ]
}